ADSoft/LinearRegressLags.py
ADSoft/SARIMA.py
ADSoft/TimeLineData.py
ADSoft/TrendChange.py
ADSoft/Utils.py
ADSoft/__init__.py
adsoft-0.0.4.dist-info/METADATA
adsoft-0.0.4.dist-info/WHEEL
adsoft-0.0.4.dist-info/licenses/LICENSE.txt
adsoft-0.0.4.dist-info/RECORD
