Metadata-Version: 2.3
Name: ADSoft
Version: 0.0.4
Author-email: ode15s@yandex.ru
License-File: LICENSE.txt
Classifier: License :: OSI Approved :: MIT License
Classifier: Operating System :: OS Independent
Classifier: Programming Language :: Python :: 3
Requires-Python: >=3.10.0
